nonocycle/__init__.py
nonocycle/nonocycle.py
nonocycle-0.0.1.dist-info/LICENSE
nonocycle-0.0.1.dist-info/METADATA
nonocycle-0.0.1.dist-info/WHEEL
nonocycle-0.0.1.dist-info/entry_points.txt
nonocycle-0.0.1.dist-info/top_level.txt
nonocycle-0.0.1.dist-info/RECORD
