Metadata-Version: 2.1
Name: nonocycle
Version: 0.0.1
Summary: Prevent cyclic imports before they happen
Author: guarin
License: MIT
Keywords: python
Requires-Python: >=3.8
License-File: LICENSE
Requires-Dist: networkx >=1.5.12
Requires-Dist: pydeps >=1.11
Provides-Extra: dev
Requires-Dist: ruff >=0.4.0 ; extra == 'dev'
